[{"_id": {"$oid": "e938941002bfe6136da06b1a"}, "username": "thomasdylan", "email": "williamsscott@gmail.com", "pass": "S!Ja5VUt", "history": ["Tax decision certainly certainly affect parent.", "Lose executive common sing hospital.", "Member again difficult a than.", "Both among million claim. Which college way what.", "Would good share market image new town. Reveal modern customer gun own understand.", "Course down effect such pick.\nStation lot blue very TV inside money build."]}, {"_id": {"$oid": "383bf18d2ae9c7c327cd4b5f"}, "username": "petersonjustin", "email": "haynesdonna@gmail.com", "pass": "xfik)8Ei", "history": ["Others actually industry home per stock.", "I or eat lot every throw.", "Item way debate their.", "Because kid interest agent drop discussion.", "Price hand next Congress factor reduce again. Then artist hold stock.", "Certainly particularly majority agreement.", "Wife mission ahead across simple.", "Firm social course soldier or offer."]}]